tox_pypi_filter/__init__.py
tox_pypi_filter/plugin.py
tox_pypi_filter-0.15.dist-info/licenses/LICENSE
tox_pypi_filter-0.15.dist-info/METADATA
tox_pypi_filter-0.15.dist-info/WHEEL
tox_pypi_filter-0.15.dist-info/entry_points.txt
tox_pypi_filter-0.15.dist-info/top_level.txt
tox_pypi_filter-0.15.dist-info/RECORD
