Metadata-Version: 2.4
Name: tox-pypi-filter
Version: 0.15
Summary: Implement a --pypi-filter option for tox
Author-email: Thomas Robitaille <thomas.robitaille@gmail.com>, Stuart Mumford <stuart@cadair.com>
License: BSD-2-Clause
Requires-Python: >=3.10
License-File: LICENSE
Requires-Dist: tox>=4.0.9
Requires-Dist: pypicky>=0.5
Requires-Dist: setuptools
Dynamic: license-file
